{"id": "lD-QnTZ6ePo", "title": "Annette Hanshaw - What'll You Do - 1927", "formats": [{"asr": 48000, "filesize": 982380, "format_id": "249", "format_note": "tiny", "fps": null, "height": null, "quality": 0, "tbr": 47.612, "url": "https://rr6---sn-0opoxu-ihv6.googlevideo.com/videoplayback?expire=1670691041&ei=gWSUY46HEoGZkwbsn6moDw&ip=189.173.225.87&id=o-AIyXpcAiFZ3oPZQUrfkAuHs5D4DONy4rc79c6ysu4j-Q&itag=249&source=youtube&requiressl=yes&mh=5K&mm=31%2C29&mn=sn-0opoxu-ihv6%2Csn-q4fl6nlz&ms=au%2Crdu&mv=m&mvi=6&pl=24&initcwndbps=940000&vprv=1&mime=audio%2Fwebm&ns=gjv1ZU8Zjt8OADKnJiiGtCAJ&gir=yes&clen=982380&dur=165.061&lmt=1644433537357314&mt=1670669112&fvip=1&keepalive=yes&fexp=24001373%2C24007246&c=WEB&txp=1432434&n=w9Ms91d7rvWAN-Zkb&sparams=expire%2Cei%2Cip%2Cid%2Citag%2Csource%2Crequiressl%2Cvprv%2Cmime%2Cns%2Cgir%2Cclen%2Cdur%2Clmt&sig=AOq0QJ8wRgIhAM_WV0Cmz-zdVOqLzX-0LrMqRCfY_RoMa0PWWobg7h_jAiEA-mNmhVnnZmbpavob4za_j1Ml9wJqm_j7rK4DJWageeE%3D&lsparams=mh%2Cmm%2Cmn%2Cms%2Cmv%2Cmvi%2Cpl%2Cinitcwndbps&lsig=AG3C_xAwRAIgR7g86WWNxdGAiQTId3ED4iMs7oFWrkNSGkGq00Qd134CIGL3aiV0Xie8Dg167jN766hn0ZqX6USIrA3e6mx7yed9", "width": null, "ext": "webm", "vcodec": "none", "acodec": "opus", "abr": 47.612, "downloader_options": {"http_chunk_size": 10485760}, "container": "webm_dash", "format": "249 - audio only (tiny)", "protocol": "https", "http_headers": {"User-Agent": "Mozilla/5.0 (Windows NT 10.0; Win64; x64) AppleWebKit/537.36 (KHTML, like Gecko) Chrome/74.0.3729.127 Safari/537.36", "Accept-Charset": "ISO-8859-1,utf-8;q=0.7,*;q=0.7", "Accept": "text/html,application/xhtml+xml,application/xml;q=0.9,*/*;q=0.8", "Accept-Encoding": "gzip, deflate", "Accept-Language": "en-us,en;q=0.5"}}, {"asr": 48000, "filesize": 1186687, "format_id": "250", "format_note": "tiny", "fps": null, "height": null, "quality": 0, "tbr": 57.515, "url": "https://rr6---sn-0opoxu-ihv6.googlevideo.com/videoplayback?expire=1670691041&ei=gWSUY46HEoGZkwbsn6moDw&ip=189.173.225.87&id=o-AIyXpcAiFZ3oPZQUrfkAuHs5D4DONy4rc79c6ysu4j-Q&itag=250&source=youtube&requiressl=yes&mh=5K&mm=31%2C29&mn=sn-0opoxu-ihv6%2Csn-q4fl6nlz&ms=au%2Crdu&mv=m&mvi=6&pl=24&initcwndbps=940000&vprv=1&mime=audio%2Fwebm&ns=gjv1ZU8Zjt8OADKnJiiGtCAJ&gir=yes&clen=1186687&dur=165.061&lmt=1644433530851080&mt=1670669112&fvip=1&keepalive=yes&fexp=24001373%2C24007246&c=WEB&txp=1432434&n=w9Ms91d7rvWAN-Zkb&sparams=expire%2Cei%2Cip%2Cid%2Citag%2Csource%2Crequiressl%2Cvprv%2Cmime%2Cns%2Cgir%2Cclen%2Cdur%2Clmt&sig=AOq0QJ8wRQIgZErrOpRt2cQgmEXIuLbydcxEC6yhorF5coQLpba60DUCIQCMaLNYSo-bD1RTTQs9sL81xFTrhUubK9XXu9diJOnS7w%3D%3D&lsparams=mh%2Cmm%2Cmn%2Cms%2Cmv%2Cmvi%2Cpl%2Cinitcwndbps&lsig=AG3C_xAwRAIgR7g86WWNxdGAiQTId3ED4iMs7oFWrkNSGkGq00Qd134CIGL3aiV0Xie8Dg167jN766hn0ZqX6USIrA3e6mx7yed9", "width": null, "ext": "webm", "vcodec": "none", "acodec": "opus", "abr": 57.515, "downloader_options": {"http_chunk_size": 10485760}, "container": "webm_dash", "format": "250 - audio only (tiny)", "protocol": "https", "http_headers": {"User-Agent": "Mozilla/5.0 (Windows NT 10.0; Win64; x64) AppleWebKit/537.36 (KHTML, like Gecko) Chrome/74.0.3729.127 Safari/537.36", "Accept-Charset": "ISO-8859-1,utf-8;q=0.7,*;q=0.7", "Accept": "text/html,application/xhtml+xml,application/xml;q=0.9,*/*;q=0.8", "Accept-Encoding": "gzip, deflate", "Accept-Language": "en-us,en;q=0.5"}}, {"asr": 48000, "filesize": 2469494, "format_id": "251", "format_note": "tiny", "fps": null, "height": null, "quality": 0, "tbr": 119.688, "url": "https://rr6---sn-0opoxu-ihv6.googlevideo.com/videoplayback?expire=1670691041&ei=gWSUY46HEoGZkwbsn6moDw&ip=189.173.225.87&id=o-AIyXpcAiFZ3oPZQUrfkAuHs5D4DONy4rc79c6ysu4j-Q&itag=251&source=youtube&requiressl=yes&mh=5K&mm=31%2C29&mn=sn-0opoxu-ihv6%2Csn-q4fl6nlz&ms=au%2Crdu&mv=m&mvi=6&pl=24&initcwndbps=940000&vprv=1&mime=audio%2Fwebm&ns=gjv1ZU8Zjt8OADKnJiiGtCAJ&gir=yes&clen=2469494&dur=165.061&lmt=1644433530648528&mt=1670669112&fvip=1&keepalive=yes&fexp=24001373%2C24007246&c=WEB&txp=1432434&n=w9Ms91d7rvWAN-Zkb&sparams=expire%2Cei%2Cip%2Cid%2Citag%2Csource%2Crequiressl%2Cvprv%2Cmime%2Cns%2Cgir%2Cclen%2Cdur%2Clmt&sig=AOq0QJ8wRAIga8E-Yqc92jigB6WpnZdNE4mwClx6JFrNN0xjk2ipFgYCIBo3lR2z6s1AytoeaGN2ksBMh6I-J8Zkj0upwbhZJEXt&lsparams=mh%2Cmm%2Cmn%2Cms%2Cmv%2Cmvi%2Cpl%2Cinitcwndbps&lsig=AG3C_xAwRAIgR7g86WWNxdGAiQTId3ED4iMs7oFWrkNSGkGq00Qd134CIGL3aiV0Xie8Dg167jN766hn0ZqX6USIrA3e6mx7yed9", "width": null, "ext": "webm", "vcodec": "none", "acodec": "opus", "abr": 119.688, "downloader_options": {"http_chunk_size": 10485760}, "container": "webm_dash", "format": "251 - audio only (tiny)", "protocol": "https", "http_headers": {"User-Agent": "Mozilla/5.0 (Windows NT 10.0; Win64; x64) AppleWebKit/537.36 (KHTML, like Gecko) Chrome/74.0.3729.127 Safari/537.36", "Accept-Charset": "ISO-8859-1,utf-8;q=0.7,*;q=0.7", "Accept": "text/html,application/xhtml+xml,application/xml;q=0.9,*/*;q=0.8", "Accept-Encoding": "gzip, deflate", "Accept-Language": "en-us,en;q=0.5"}}, {"asr": 44100, "filesize": 2622700, "format_id": "140", "format_note": "tiny", "fps": null, "height": null, "quality": 0, "tbr": 127.089, "url": "https://rr6---sn-0opoxu-ihv6.googlevideo.com/videoplayback?expire=1670691041&ei=gWSUY46HEoGZkwbsn6moDw&ip=189.173.225.87&id=o-AIyXpcAiFZ3oPZQUrfkAuHs5D4DONy4rc79c6ysu4j-Q&itag=140&source=youtube&requiressl=yes&mh=5K&mm=31%2C29&mn=sn-0opoxu-ihv6%2Csn-q4fl6nlz&ms=au%2Crdu&mv=m&mvi=6&pl=24&initcwndbps=940000&vprv=1&mime=audio%2Fmp4&ns=gjv1ZU8Zjt8OADKnJiiGtCAJ&gir=yes&clen=2622700&dur=165.093&lmt=1386701337409611&mt=1670669112&fvip=1&keepalive=yes&fexp=24001373%2C24007246&c=WEB&n=w9Ms91d7rvWAN-Zkb&sparams=expire%2Cei%2Cip%2Cid%2Citag%2Csource%2Crequiressl%2Cvprv%2Cmime%2Cns%2Cgir%2Cclen%2Cdur%2Clmt&sig=AOq0QJ8wRAIga9uAKsMSuKiNLoMMzMsYTn02w4BGrwM1_yIJ2bB2a4UCIGzH0rJKENW2W-WIBaFhr08SfZSMrP0Lvyi23xRPr2rl&lsparams=mh%2Cmm%2Cmn%2Cms%2Cmv%2Cmvi%2Cpl%2Cinitcwndbps&lsig=AG3C_xAwRAIgR7g86WWNxdGAiQTId3ED4iMs7oFWrkNSGkGq00Qd134CIGL3aiV0Xie8Dg167jN766hn0ZqX6USIrA3e6mx7yed9", "width": null, "ext": "m4a", "vcodec": "none", "acodec": "mp4a.40.2", "abr": 127.089, "downloader_options": {"http_chunk_size": 10485760}, "container": "m4a_dash", "format": "140 - audio only (tiny)", "protocol": "https", "http_headers": {"User-Agent": "Mozilla/5.0 (Windows NT 10.0; Win64; x64) AppleWebKit/537.36 (KHTML, like Gecko) Chrome/74.0.3729.127 Safari/537.36", "Accept-Charset": "ISO-8859-1,utf-8;q=0.7,*;q=0.7", "Accept": "text/html,application/xhtml+xml,application/xml;q=0.9,*/*;q=0.8", "Accept-Encoding": "gzip, deflate", "Accept-Language": "en-us,en;q=0.5"}}, {"asr": null, "filesize": 1141874, "format_id": "278", "format_note": "144p", "fps": 30, "height": 144, "quality": 0, "tbr": 55.353, "url": "https://rr6---sn-0opoxu-ihv6.googlevideo.com/videoplayback?expire=1670691041&ei=gWSUY46HEoGZkwbsn6moDw&ip=189.173.225.87&id=o-AIyXpcAiFZ3oPZQUrfkAuHs5D4DONy4rc79c6ysu4j-Q&itag=278&aitags=133%2C134%2C160%2C242%2C243%2C278&source=youtube&requiressl=yes&mh=5K&mm=31%2C29&mn=sn-0opoxu-ihv6%2Csn-q4fl6nlz&ms=au%2Crdu&mv=m&mvi=6&pl=24&initcwndbps=940000&vprv=1&mime=video%2Fwebm&ns=gjv1ZU8Zjt8OADKnJiiGtCAJ&gir=yes&clen=1141874&dur=165.031&lmt=1644433971536803&mt=1670669112&fvip=1&keepalive=yes&fexp=24001373%2C24007246&c=WEB&txp=1432434&n=w9Ms91d7rvWAN-Zkb&sparams=expire%2Cei%2Cip%2Cid%2Caitags%2Csource%2Crequiressl%2Cvprv%2Cmime%2Cns%2Cgir%2Cclen%2Cdur%2Clmt&sig=AOq0QJ8wRQIgU9Lt-if-bbjFxuZcZpxNvxAWlairB2rdGEhT8L1Nb9kCIQDmYD5nQ9wzkBsHuHN9KSkElT4xPMXkXt8MAzYgrYeGcQ%3D%3D&lsparams=mh%2Cmm%2Cmn%2Cms%2Cmv%2Cmvi%2Cpl%2Cinitcwndbps&lsig=AG3C_xAwRAIgR7g86WWNxdGAiQTId3ED4iMs7oFWrkNSGkGq00Qd134CIGL3aiV0Xie8Dg167jN766hn0ZqX6USIrA3e6mx7yed9", "width": 256, "ext": "webm", "vcodec": "vp9", "acodec": "none", "vbr": 55.353, "downloader_options": {"http_chunk_size": 10485760}, "container": "webm_dash", "format": "278 - 256x144 (144p)", "protocol": "https", "http_headers": {"User-Agent": "Mozilla/5.0 (Windows NT 10.0; Win64; x64) AppleWebKit/537.36 (KHTML, like Gecko) Chrome/74.0.3729.127 Safari/537.36", "Accept-Charset": "ISO-8859-1,utf-8;q=0.7,*;q=0.7", "Accept": "text/html,application/xhtml+xml,application/xml;q=0.9,*/*;q=0.8", "Accept-Encoding": "gzip, deflate", "Accept-Language": "en-us,en;q=0.5"}}, {"asr": null, "filesize": 2318650, "format_id": "160", "format_note": "144p", "fps": 15, "height": 144, "quality": 0, "tbr": 112.42, "url": "https://rr6---sn-0opoxu-ihv6.googlevideo.com/videoplayback?expire=1670691041&ei=gWSUY46HEoGZkwbsn6moDw&ip=189.173.225.87&id=o-AIyXpcAiFZ3oPZQUrfkAuHs5D4DONy4rc79c6ysu4j-Q&itag=160&aitags=133%2C134%2C160%2C242%2C243%2C278&source=youtube&requiressl=yes&mh=5K&mm=31%2C29&mn=sn-0opoxu-ihv6%2Csn-q4fl6nlz&ms=au%2Crdu&mv=m&mvi=6&pl=24&initcwndbps=940000&vprv=1&mime=video%2Fmp4&ns=gjv1ZU8Zjt8OADKnJiiGtCAJ&gir=yes&clen=2318650&dur=164.998&lmt=1386701346207812&mt=1670669112&fvip=1&keepalive=yes&fexp=24001373%2C24007246&c=WEB&n=w9Ms91d7rvWAN-Zkb&sparams=expire%2Cei%2Cip%2Cid%2Caitags%2Csource%2Crequiressl%2Cvprv%2Cmime%2Cns%2Cgir%2Cclen%2Cdur%2Clmt&sig=AOq0QJ8wRQIhAJqT2skyeR1h0E33GizVjz1LlgPm_uP57oNMMtiFRCwlAiBGmN4Kv9E6vX4psG2UE-sQBCnirTX2ERAVKaLeK2EheA%3D%3D&lsparams=mh%2Cmm%2Cmn%2Cms%2Cmv%2Cmvi%2Cpl%2Cinitcwndbps&lsig=AG3C_xAwRAIgR7g86WWNxdGAiQTId3ED4iMs7oFWrkNSGkGq00Qd134CIGL3aiV0Xie8Dg167jN766hn0ZqX6USIrA3e6mx7yed9", "width": 256, "ext": "mp4", "vcodec": "avc1.4d400c", "acodec": "none", "vbr": 112.42, "downloader_options": {"http_chunk_size": 10485760}, "container": "mp4_dash", "format": "160 - 256x144 (144p)", "protocol": "https", "http_headers": {"User-Agent": "Mozilla/5.0 (Windows NT 10.0; Win64; x64) AppleWebKit/537.36 (KHTML, like Gecko) Chrome/74.0.3729.127 Safari/537.36", "Accept-Charset": "ISO-8859-1,utf-8;q=0.7,*;q=0.7", "Accept": "text/html,application/xhtml+xml,application/xml;q=0.9,*/*;q=0.8", "Accept-Encoding": "gzip, deflate", "Accept-Language": "en-us,en;q=0.5"}}, {"asr": null, "filesize": 916595, "format_id": "242", "format_note": "240p", "fps": 30, "height": 240, "quality": 1, "tbr": 44.432, "url": "https://rr6---sn-0opoxu-ihv6.googlevideo.com/videoplayback?expire=1670691041&ei=gWSUY46HEoGZkwbsn6moDw&ip=189.173.225.87&id=o-AIyXpcAiFZ3oPZQUrfkAuHs5D4DONy4rc79c6ysu4j-Q&itag=242&aitags=133%2C134%2C160%2C242%2C243%2C278&source=youtube&requiressl=yes&mh=5K&mm=31%2C29&mn=sn-0opoxu-ihv6%2Csn-q4fl6nlz&ms=au%2Crdu&mv=m&mvi=6&pl=24&initcwndbps=940000&vprv=1&mime=video%2Fwebm&ns=gjv1ZU8Zjt8OADKnJiiGtCAJ&gir=yes&clen=916595&dur=165.031&lmt=1644433972764169&mt=1670669112&fvip=1&keepalive=yes&fexp=24001373%2C24007246&c=WEB&txp=1432434&n=w9Ms91d7rvWAN-Zkb&sparams=expire%2Cei%2Cip%2Cid%2Caitags%2Csource%2Crequiressl%2Cvprv%2Cmime%2Cns%2Cgir%2Cclen%2Cdur%2Clmt&sig=AOq0QJ8wRAIgB3eNaRh25mAWMAY2NC2bhG6C3Av938s3FTE91a6PatkCIEaAo9F2gm7eXXAfptHCMUtzWYEhv17Iot_dD3VFOfHB&lsparams=mh%2Cmm%2Cmn%2Cms%2Cmv%2Cmvi%2Cpl%2Cinitcwndbps&lsig=AG3C_xAwRAIgR7g86WWNxdGAiQTId3ED4iMs7oFWrkNSGkGq00Qd134CIGL3aiV0Xie8Dg167jN766hn0ZqX6USIrA3e6mx7yed9", "width": 426, "ext": "webm", "vcodec": "vp9", "acodec": "none", "vbr": 44.432, "downloader_options": {"http_chunk_size": 10485760}, "container": "webm_dash", "format": "242 - 426x240 (240p)", "protocol": "https", "http_headers": {"User-Agent": "Mozilla/5.0 (Windows NT 10.0; Win64; x64) AppleWebKit/537.36 (KHTML, like Gecko) Chrome/74.0.3729.127 Safari/537.36", "Accept-Charset": "ISO-8859-1,utf-8;q=0.7,*;q=0.7", "Accept": "text/html,application/xhtml+xml,application/xml;q=0.9,*/*;q=0.8", "Accept-Encoding": "gzip, deflate", "Accept-Language": "en-us,en;q=0.5"}}, {"asr": null, "filesize": 5047531, "format_id": "133", "format_note": "240p", "fps": 30, "height": 240, "quality": 1, "tbr": 244.731, "url": "https://rr6---sn-0opoxu-ihv6.googlevideo.com/videoplayback?expire=1670691041&ei=gWSUY46HEoGZkwbsn6moDw&ip=189.173.225.87&id=o-AIyXpcAiFZ3oPZQUrfkAuHs5D4DONy4rc79c6ysu4j-Q&itag=133&aitags=133%2C134%2C160%2C242%2C243%2C278&source=youtube&requiressl=yes&mh=5K&mm=31%2C29&mn=sn-0opoxu-ihv6%2Csn-q4fl6nlz&ms=au%2Crdu&mv=m&mvi=6&pl=24&initcwndbps=940000&vprv=1&mime=video%2Fmp4&ns=gjv1ZU8Zjt8OADKnJiiGtCAJ&gir=yes&clen=5047531&dur=164.998&lmt=1386701339548733&mt=1670669112&fvip=1&keepalive=yes&fexp=24001373%2C24007246&c=WEB&n=w9Ms91d7rvWAN-Zkb&sparams=expire%2Cei%2Cip%2Cid%2Caitags%2Csource%2Crequiressl%2Cvprv%2Cmime%2Cns%2Cgir%2Cclen%2Cdur%2Clmt&sig=AOq0QJ8wRQIgSxlu3ZqWOl1AvJm53uDTbr2KT72YhkGZL4t2rfvAPMYCIQCS2U3QRBIbLPGuXvLdSH2EuI5OZ38fTGGSh79I2pBvpg%3D%3D&lsparams=mh%2Cmm%2Cmn%2Cms%2Cmv%2Cmvi%2Cpl%2Cinitcwndbps&lsig=AG3C_xAwRAIgR7g86WWNxdGAiQTId3ED4iMs7oFWrkNSGkGq00Qd134CIGL3aiV0Xie8Dg167jN766hn0ZqX6USIrA3e6mx7yed9", "width": 426, "ext": "mp4", "vcodec": "avc1.4d4015", "acodec": "none", "vbr": 244.731, "downloader_options": {"http_chunk_size": 10485760}, "container": "mp4_dash", "format": "133 - 426x240 (240p)", "protocol": "https", "http_headers": {"User-Agent": "Mozilla/5.0 (Windows NT 10.0; Win64; x64) AppleWebKit/537.36 (KHTML, like Gecko) Chrome/74.0.3729.127 Safari/537.36", "Accept-Charset": "ISO-8859-1,utf-8;q=0.7,*;q=0.7", "Accept": "text/html,application/xhtml+xml,application/xml;q=0.9,*/*;q=0.8", "Accept-Encoding": "gzip, deflate", "Accept-Language": "en-us,en;q=0.5"}}, {"asr": null, "filesize": 1651679, "format_id": "243", "format_note": "360p", "fps": 30, "height": 360, "quality": 2, "tbr": 80.066, "url": "https://rr6---sn-0opoxu-ihv6.googlevideo.com/videoplayback?expire=1670691041&ei=gWSUY46HEoGZkwbsn6moDw&ip=189.173.225.87&id=o-AIyXpcAiFZ3oPZQUrfkAuHs5D4DONy4rc79c6ysu4j-Q&itag=243&aitags=133%2C134%2C160%2C242%2C243%2C278&source=youtube&requiressl=yes&mh=5K&mm=31%2C29&mn=sn-0opoxu-ihv6%2Csn-q4fl6nlz&ms=au%2Crdu&mv=m&mvi=6&pl=24&initcwndbps=940000&vprv=1&mime=video%2Fwebm&ns=gjv1ZU8Zjt8OADKnJiiGtCAJ&gir=yes&clen=1651679&dur=165.031&lmt=1644433996856663&mt=1670669112&fvip=1&keepalive=yes&fexp=24001373%2C24007246&c=WEB&txp=1432434&n=w9Ms91d7rvWAN-Zkb&sparams=expire%2Cei%2Cip%2Cid%2Caitags%2Csource%2Crequiressl%2Cvprv%2Cmime%2Cns%2Cgir%2Cclen%2Cdur%2Clmt&sig=AOq0QJ8wRgIhAI60htGAJ0SyjJV0Uk3ieus-A-S4aasCz-jVbNv1orplAiEA1LuCSP8PlCP4DdY2fHXCbM_M83MTCXaFKRFRC0JqqQk%3D&lsparams=mh%2Cmm%2Cmn%2Cms%2Cmv%2Cmvi%2Cpl%2Cinitcwndbps&lsig=AG3C_xAwRAIgR7g86WWNxdGAiQTId3ED4iMs7oFWrkNSGkGq00Qd134CIGL3aiV0Xie8Dg167jN766hn0ZqX6USIrA3e6mx7yed9", "width": 640, "ext": "webm", "vcodec": "vp9", "acodec": "none", "vbr": 80.066, "downloader_options": {"http_chunk_size": 10485760}, "container": "webm_dash", "format": "243 - 640x360 (360p)", "protocol": "https", "http_headers": {"User-Agent": "Mozilla/5.0 (Windows NT 10.0; Win64; x64) AppleWebKit/537.36 (KHTML, like Gecko) Chrome/74.0.3729.127 Safari/537.36", "Accept-Charset": "ISO-8859-1,utf-8;q=0.7,*;q=0.7", "Accept": "text/html,application/xhtml+xml,application/xml;q=0.9,*/*;q=0.8", "Accept-Encoding": "gzip, deflate", "Accept-Language": "en-us,en;q=0.5"}}, {"asr": null, "filesize": 5487059, "format_id": "134", "format_note": "360p", "fps": 30, "height": 360, "quality": 2, "tbr": 266.042, "url": "https://rr6---sn-0opoxu-ihv6.googlevideo.com/videoplayback?expire=1670691041&ei=gWSUY46HEoGZkwbsn6moDw&ip=189.173.225.87&id=o-AIyXpcAiFZ3oPZQUrfkAuHs5D4DONy4rc79c6ysu4j-Q&itag=134&aitags=133%2C134%2C160%2C242%2C243%2C278&source=youtube&requiressl=yes&mh=5K&mm=31%2C29&mn=sn-0opoxu-ihv6%2Csn-q4fl6nlz&ms=au%2Crdu&mv=m&mvi=6&pl=24&initcwndbps=940000&vprv=1&mime=video%2Fmp4&ns=gjv1ZU8Zjt8OADKnJiiGtCAJ&gir=yes&clen=5487059&dur=164.998&lmt=1386701352352544&mt=1670669112&fvip=1&keepalive=yes&fexp=24001373%2C24007246&c=WEB&n=w9Ms91d7rvWAN-Zkb&sparams=expire%2Cei%2Cip%2Cid%2Caitags%2Csource%2Crequiressl%2Cvprv%2Cmime%2Cns%2Cgir%2Cclen%2Cdur%2Clmt&sig=AOq0QJ8wRQIhAJzkthbl9CiQh2ID7YzcL0j1BYg-enmvS9ZHMnAjcsk0AiAbKeFjayI-0b3a_Hyjo8AoRoY-ASvicUigUOtLbWrYsg%3D%3D&lsparams=mh%2Cmm%2Cmn%2Cms%2Cmv%2Cmvi%2Cpl%2Cinitcwndbps&lsig=AG3C_xAwRAIgR7g86WWNxdGAiQTId3ED4iMs7oFWrkNSGkGq00Qd134CIGL3aiV0Xie8Dg167jN766hn0ZqX6USIrA3e6mx7yed9", "width": 640, "ext": "mp4", "vcodec": "avc1.4d401e", "acodec": "none", "vbr": 266.042, "downloader_options": {"http_chunk_size": 10485760}, "container": "mp4_dash", "format": "134 - 640x360 (360p)", "protocol": "https", "http_headers": {"User-Agent": "Mozilla/5.0 (Windows NT 10.0; Win64; x64) AppleWebKit/537.36 (KHTML, like Gecko) Chrome/74.0.3729.127 Safari/537.36", "Accept-Charset": "ISO-8859-1,utf-8;q=0.7,*;q=0.7", "Accept": "text/html,application/xhtml+xml,application/xml;q=0.9,*/*;q=0.8", "Accept-Encoding": "gzip, deflate", "Accept-Language": "en-us,en;q=0.5"}}, {"asr": 44100, "filesize": null, "format_id": "18", "format_note": "360p", "fps": 30, "height": 360, "quality": 2, "tbr": 391.84, "url": "https://rr6---sn-0opoxu-ihv6.googlevideo.com/videoplayback?expire=1670691041&ei=gWSUY46HEoGZkwbsn6moDw&ip=189.173.225.87&id=o-AIyXpcAiFZ3oPZQUrfkAuHs5D4DONy4rc79c6ysu4j-Q&itag=18&source=youtube&requiressl=yes&mh=5K&mm=31%2C29&mn=sn-0opoxu-ihv6%2Csn-q4fl6nlz&ms=au%2Crdu&mv=m&mvi=6&pl=24&initcwndbps=940000&vprv=1&mime=video%2Fmp4&ns=8jcLCC_vs_WZb5Qav7mFa58J&cnr=14&ratebypass=yes&dur=165.093&lmt=1664132564500247&mt=1670669112&fvip=1&fexp=24001373%2C24007246&c=WEB&txp=1438434&n=v9rNWpJ9jNNyN-9jI&sparams=expire%2Cei%2Cip%2Cid%2Citag%2Csource%2Crequiressl%2Cvprv%2Cmime%2Cns%2Ccnr%2Cratebypass%2Cdur%2Clmt&sig=AOq0QJ8wRQIgN_U432dXaAOg5Fh0W7kCE1sK_62UeIycyOyq69SIDzsCIQDIzIWXrNqRd8m0sa2xJMTzjQ3_uTtrLBx0YRYKqjon1A%3D%3D&lsparams=mh%2Cmm%2Cmn%2Cms%2Cmv%2Cmvi%2Cpl%2Cinitcwndbps&lsig=AG3C_xAwRAIgR7g86WWNxdGAiQTId3ED4iMs7oFWrkNSGkGq00Qd134CIGL3aiV0Xie8Dg167jN766hn0ZqX6USIrA3e6mx7yed9", "width": 640, "ext": "mp4", "vcodec": "avc1.42001E", "acodec": "mp4a.40.2", "format": "18 - 640x360 (360p)", "protocol": "https", "http_headers": {"User-Agent": "Mozilla/5.0 (Windows NT 10.0; Win64; x64) AppleWebKit/537.36 (KHTML, like Gecko) Chrome/74.0.3729.127 Safari/537.36", "Accept-Charset": "ISO-8859-1,utf-8;q=0.7,*;q=0.7", "Accept": "text/html,application/xhtml+xml,application/xml;q=0.9,*/*;q=0.8", "Accept-Encoding": "gzip, deflate", "Accept-Language": "en-us,en;q=0.5"}}], "thumbnails": [{"height": 94, "url": "https://i.ytimg.com/vi/lD-QnTZ6ePo/hqdefault.jpg?sqp=-oaymwEbCKgBEF5IVfKriqkDDggBFQAAiEIYAXABwAEG&rs=AOn4CLCzIViYlVmtmkjEia2HkS4TNcODsw", "width": 168, "resolution": "168x94", "id": "0"}, {"height": 110, "url": "https://i.ytimg.com/vi/lD-QnTZ6ePo/hqdefault.jpg?sqp=-oaymwEbCMQBEG5IVfKriqkDDggBFQAAiEIYAXABwAEG&rs=AOn4CLAlwXsrIeJZLjGHq5G9vc1292ZHYQ", "width": 196, "resolution": "196x110", "id": "1"}, {"height": 138, "url": "https://i.ytimg.com/vi/lD-QnTZ6ePo/hqdefault.jpg?sqp=-oaymwEcCPYBEIoBSFXyq4qpAw4IARUAAIhCGAFwAcABBg==&rs=AOn4CLA0ZbbHg-Vwv1yLiKSzl23qlDRnAg", "width": 246, "resolution": "246x138", "id": "2"}, {"height": 188, "url": "https://i.ytimg.com/vi/lD-QnTZ6ePo/hqdefault.jpg?sqp=-oaymwEcCNACELwBSFXyq4qpAw4IARUAAIhCGAFwAcABBg==&rs=AOn4CLC2s3noYyk9-QhcvuHlqdtvWIeT0w", "width": 336, "resolution": "336x188", "id": "3"}], "description": "Annette Hanshaw with Lou Gold and his orchestra\nMusic and Lyrics: (Chester Cohn (AKA: Cahn, Kahn) & Nathan 'Ned' Miller)\nPerfect #14907,  1927", "upload_date": "20120912", "uploader": "QUABLEDISTOCFICKLEPO", "uploader_id": "QUABLEDISTOCFICKLEPO", "uploader_url": "http://www.youtube.com/user/QUABLEDISTOCFICKLEPO", "channel_id": "UCHGj-IOIi4PkZQVgbkqJ7pw", "channel_url": "https://www.youtube.com/channel/UCHGj-IOIi4PkZQVgbkqJ7pw", "duration": 165, "view_count": 12924, "average_rating": null, "age_limit": 0, "webpage_url": "https://www.youtube.com/watch?v=lD-QnTZ6ePo", "categories": ["Music"], "tags": ["Annette Hanshaw", "1920s music What'll You Do?"], "is_live": null, "channel": "QUABLEDISTOCFICKLEPO", "extractor": "youtube", "webpage_url_basename": "watch", "extractor_key": "Youtube", "playlist": null, "playlist_index": null, "thumbnail": "https://i.ytimg.com/vi/lD-QnTZ6ePo/hqdefault.jpg?sqp=-oaymwEcCNACELwBSFXyq4qpAw4IARUAAIhCGAFwAcABBg==&rs=AOn4CLC2s3noYyk9-QhcvuHlqdtvWIeT0w", "display_id": "lD-QnTZ6ePo", "asr": 44100, "filesize": null, "format_id": "18", "format_note": "360p", "fps": 30, "height": 360, "quality": 2, "tbr": 391.84, "url": "https://rr6---sn-0opoxu-ihv6.googlevideo.com/videoplayback?expire=1670691041&ei=gWSUY46HEoGZkwbsn6moDw&ip=189.173.225.87&id=o-AIyXpcAiFZ3oPZQUrfkAuHs5D4DONy4rc79c6ysu4j-Q&itag=18&source=youtube&requiressl=yes&mh=5K&mm=31%2C29&mn=sn-0opoxu-ihv6%2Csn-q4fl6nlz&ms=au%2Crdu&mv=m&mvi=6&pl=24&initcwndbps=940000&vprv=1&mime=video%2Fmp4&ns=8jcLCC_vs_WZb5Qav7mFa58J&cnr=14&ratebypass=yes&dur=165.093&lmt=1664132564500247&mt=1670669112&fvip=1&fexp=24001373%2C24007246&c=WEB&txp=1438434&n=v9rNWpJ9jNNyN-9jI&sparams=expire%2Cei%2Cip%2Cid%2Citag%2Csource%2Crequiressl%2Cvprv%2Cmime%2Cns%2Ccnr%2Cratebypass%2Cdur%2Clmt&sig=AOq0QJ8wRQIgN_U432dXaAOg5Fh0W7kCE1sK_62UeIycyOyq69SIDzsCIQDIzIWXrNqRd8m0sa2xJMTzjQ3_uTtrLBx0YRYKqjon1A%3D%3D&lsparams=mh%2Cmm%2Cmn%2Cms%2Cmv%2Cmvi%2Cpl%2Cinitcwndbps&lsig=AG3C_xAwRAIgR7g86WWNxdGAiQTId3ED4iMs7oFWrkNSGkGq00Qd134CIGL3aiV0Xie8Dg167jN766hn0ZqX6USIrA3e6mx7yed9", "width": 640, "ext": "mp4", "vcodec": "avc1.42001E", "acodec": "mp4a.40.2", "format": "18 - 640x360 (360p)", "protocol": "https", "http_headers": {"User-Agent": "Mozilla/5.0 (Windows NT 10.0; Win64; x64) AppleWebKit/537.36 (KHTML, like Gecko) Chrome/74.0.3729.127 Safari/537.36", "Accept-Charset": "ISO-8859-1,utf-8;q=0.7,*;q=0.7", "Accept": "text/html,application/xhtml+xml,application/xml;q=0.9,*/*;q=0.8", "Accept-Encoding": "gzip, deflate", "Accept-Language": "en-us,en;q=0.5"}, "fulltitle": "Annette Hanshaw - What'll You Do - 1927", "_filename": "Annette Hanshaw - What'll You Do - 1927-lD-QnTZ6ePo.mp4"}